octavia_ovn_provider/__init__.py
octavia_ovn_provider/driver/__init__.py
octavia_ovn_provider-0.0.0.dist-info/AUTHORS
octavia_ovn_provider-0.0.0.dist-info/LICENSE
octavia_ovn_provider-0.0.0.dist-info/METADATA
octavia_ovn_provider-0.0.0.dist-info/WHEEL
octavia_ovn_provider-0.0.0.dist-info/entry_points.txt
octavia_ovn_provider-0.0.0.dist-info/pbr.json
octavia_ovn_provider-0.0.0.dist-info/top_level.txt
octavia_ovn_provider-0.0.0.dist-info/RECORD
